example/__main__.py
example/example_service.py
harmony_service_lib/__init__.py
harmony_service_lib/adapter.py
harmony_service_lib/aws.py
harmony_service_lib/cli.py
harmony_service_lib/earthdata.py
harmony_service_lib/exceptions.py
harmony_service_lib/http.py
harmony_service_lib/logging.py
harmony_service_lib/message.py
harmony_service_lib/message_utility.py
harmony_service_lib/provenance.py
harmony_service_lib/s3_stac_io.py
harmony_service_lib/util.py
harmony_service_lib/version.py
harmony_service_lib-2.11.0.dist-info/licenses/LICENSE
harmony_service_lib-2.11.0.dist-info/METADATA
harmony_service_lib-2.11.0.dist-info/WHEEL
harmony_service_lib-2.11.0.dist-info/entry_points.txt
harmony_service_lib-2.11.0.dist-info/top_level.txt
harmony_service_lib-2.11.0.dist-info/RECORD
