Metadata-Version: 2.4
Name: harmony-service-lib
Version: 2.11.0
Summary: A library for Python-based Harmony services to parse incoming message, fetch data, stage data, and call back to Harmony.
Author-email: NASA EOSDIS Harmony Team <christopher.d.durbin@nasa.gov>
License: License :: OSI Approved :: Apache Software License
Project-URL: Homepage, https://github.com/nasa/harmony-service-lib-py
Classifier: Programming Language :: Python
Classifier: Programming Language :: Python :: 3
Classifier: Operating System :: OS Independent
Requires-Python: >=3.9
License-File: LICENSE
Requires-Dist: boto3
Requires-Dist: deprecation~=2.1.0
Requires-Dist: pynacl~=1.4
Requires-Dist: pystac>=1.0.0
Requires-Dist: python-json-logger~=2.0.1
Requires-Dist: requests~=2.31
Requires-Dist: urllib3~=2.6.1
Provides-Extra: dev
Requires-Dist: autopep8~=1.5; extra == "dev"
Requires-Dist: debugpy~=1.2; extra == "dev"
Requires-Dist: Faker~=8.1.3; extra == "dev"
Requires-Dist: flake8>=6.1.0; extra == "dev"
Requires-Dist: freezegun~=1.5.1; extra == "dev"
Requires-Dist: ipython~=8.10.0; extra == "dev"
Requires-Dist: jedi~=0.17.2; extra == "dev"
Requires-Dist: packaging~=24.1; extra == "dev"
Requires-Dist: parameterized~=0.7; extra == "dev"
Requires-Dist: pytest~=7.2.0; extra == "dev"
Requires-Dist: pytest-cov~=2.11; extra == "dev"
Requires-Dist: pytest-mock~=3.5; extra == "dev"
Requires-Dist: python-language-server~=0.35; extra == "dev"
Requires-Dist: responses~=0.22.0; extra == "dev"
Requires-Dist: pycodestyle>=2.9.1; extra == "dev"
Requires-Dist: setuptools==78.1.1; extra == "dev"
Requires-Dist: safety-schemas==0.0.5; extra == "dev"
Requires-Dist: safety==3.2.3; extra == "dev"
Dynamic: license-file
